AUTHORS
LICENSE
MANIFEST.in
README.rst
requirements-27.txt
requirements-dev.txt
requirements.txt
setup.cfg
setup.py
tasks.py
tox.ini
docs/ravello.rst
docs/rdomanager.rst
lib/ravstack/__init__.py
lib/ravstack/args.py
lib/ravstack/checkpw.py
lib/ravstack/compat.py
lib/ravstack/config.py
lib/ravstack/defaults.py
lib/ravstack/endpoint.py
lib/ravstack/factory.py
lib/ravstack/fixup.py
lib/ravstack/main.py
lib/ravstack/node.py
lib/ravstack/proxy.py
lib/ravstack/ravello.py
lib/ravstack/runtime.py
lib/ravstack/setup.py
lib/ravstack/util.py
lib/ravstack.egg-info/PKG-INFO
lib/ravstack.egg-info/SOURCES.txt
lib/ravstack.egg-info/dependency_links.txt
lib/ravstack.egg-info/entry_points.txt
lib/ravstack.egg-info/pbr.json
lib/ravstack.egg-info/requires.txt
lib/ravstack.egg-info/top_level.txt
share/authnz_external.conf
share/clean.sh
share/dnsmasq.conf
share/geniso
share/isolinux.cfg
share/ovirt-display-hook.py
share/ovirt-warmup.service
share/ravstack.conf.sample
share/ravstack.service
share/script.ipxe