Metadata-Version: 1.1
Name: ravstack
Version: 1.1
Summary: Run OpenStack and oVirt on Ravello Systems.
Home-page: https://github.com/geertj/ravstack
Author: Geert Jansen
Author-email: geertj@gmail.com
License: MIT
Platform: UNKNOWN
Classifier: Development Status :: 5 - Production/Stable
Classifier: License :: OSI Approved :: MIT License
Classifier: Operating System :: POSIX
Classifier: Programming Language :: Python :: 2.7
Classifier: Programming Language :: Python :: 3.3
Classifier: Programming Language :: Python :: 3.4
